termqt/__init__.py
termqt/colors.py
termqt/terminal_buffer.py
termqt/terminal_io.py
termqt/terminal_io_posix.py
termqt/terminal_io_windows.py
termqt/terminal_widget.py
termqt-1.1.dist-info/licenses/LICENSE
termqt-1.1.dist-info/METADATA
termqt-1.1.dist-info/WHEEL
termqt-1.1.dist-info/top_level.txt
termqt-1.1.dist-info/RECORD
