Metadata-Version: 2.4
Name: termqt
Version: 1.1
Summary: A terminal emulator widget implemented in Python/Qt.
Author-email: Terry Geng <terry@terriex.com>
Project-URL: Homepage, https://github.com/TerryGeng/termqt
Project-URL: Issues, https://github.com/TerryGeng/termqt/issues
Classifier: Environment :: X11 Applications :: Qt
Classifier: Programming Language :: Python :: 3
Classifier: License :: OSI Approved :: GNU Lesser General Public License v2 or later (LGPLv2+)
Classifier: Operating System :: OS Independent
Requires-Python: >=3.7
License-File: LICENSE
Requires-Dist: qtpy
Requires-Dist: pywinpty>=2.0.1; platform_system == "Windows"
Dynamic: license-file
